elexclarity/__init__.py
elexclarity/cli.py
elexclarity/client.py
elexclarity/convert.py
elexclarity/exc.py
elexclarity/utils.py
elexclarity/formatters/__init__.py
elexclarity/formatters/base.py
elexclarity/formatters/const.py
elexclarity/formatters/results.py
elexclarity/formatters/settings.py
elex_clarity-0.0.9.dist-info/LICENSE
elex_clarity-0.0.9.dist-info/METADATA
elex_clarity-0.0.9.dist-info/WHEEL
elex_clarity-0.0.9.dist-info/entry_points.txt
elex_clarity-0.0.9.dist-info/top_level.txt
elex_clarity-0.0.9.dist-info/RECORD
