Metadata-Version: 2.1
Name: elex-clarity
Version: 0.0.9
Summary: A CLI for pulling in election results from Clarity
Home-page: UNKNOWN
License: MIT
Platform: UNKNOWN
Classifier: Intended Audience :: Developers
Classifier: License :: OSI Approved :: MIT License
Classifier: Programming Language :: Python
Classifier: Programming Language :: Python :: 3.7
License-File: LICENSE
Requires-Dist: click (<8)
Requires-Dist: requests (<3)
Requires-Dist: python-dateutil
Requires-Dist: python-slugify
Requires-Dist: xmltodict
Provides-Extra: dev
Requires-Dist: sphinx ; extra == 'dev'
Requires-Dist: pytest ; extra == 'dev'
Requires-Dist: pytest-cov ; extra == 'dev'
Requires-Dist: pycodestyle ; extra == 'dev'
Requires-Dist: betamax ; extra == 'dev'
Requires-Dist: betamax-serializers ; extra == 'dev'
Requires-Dist: autopep8 ; extra == 'dev'
Requires-Dist: pylint ; extra == 'dev'
Requires-Dist: tox ; extra == 'dev'
Requires-Dist: twine ; extra == 'dev'
Provides-Extra: tests
Requires-Dist: pytest ; extra == 'tests'
Requires-Dist: pytest-cov ; extra == 'tests'
Requires-Dist: pycodestyle ; extra == 'tests'
Requires-Dist: betamax ; extra == 'tests'
Requires-Dist: betamax-serializers ; extra == 'tests'
